{
  "meta": {
    "build": {
      "build-date": "2021-07-13",
      "codified-date": "2021-06-10",
      "platform": {
        "reproducible": "true",
        "version": "2.2.2"
      },
      "repositories": [
        {
          "commit": "4398bfd4c0974c28198cc6dfdff1518a0d1428fe",
          "name": "sanipueblo/law-xml"
        },
        {
          "commit": "0117531f47707bc729b2a97d8a79036da03b0d9a",
          "name": "sanipueblo/law-xml-codified"
        }
      ]
    },
    "canonical-urls": {
      "html": "https://law.sanipueblo.org",
      "html-bulk": "https://github.com/sanipueblo/law-html",
      "static-assets": "https://github.com/sanipueblo/law-static-assets",
      "xml-bulk": "https://github.com/sanipueblo/law-xml"
    },
    "contact": {
      "email": "help@openlawlib.org"
    },
    "description": "",
    "history-start": "2017-04-19"
  }
}